llama_index/embeddings/upstage/__init__.py
llama_index/embeddings/upstage/base.py
llama_index/embeddings/upstage/utils.py
llama_index_embeddings_upstage-0.5.1.dist-info/METADATA
llama_index_embeddings_upstage-0.5.1.dist-info/WHEEL
llama_index_embeddings_upstage-0.5.1.dist-info/licenses/LICENSE
llama_index_embeddings_upstage-0.5.1.dist-info/RECORD
